{"$schema":"https://json-schema.org/draft/2020-12/schema","$id":"https://thecitizenaudit.org/schemas/platform-unknown.schema.json","title":"The Citizen Audit unknown record","type":"object","additionalProperties":false,"required":["schemaVersion","unknownId","description","category","reasonUnresolved","effectOnConclusion","evidenceNeeded","auditIds","findingIds","status"],"properties":{"schemaVersion":{"$ref":"https://thecitizenaudit.org/schemas/platform-common.schema.json#/$defs/schemaVersion"},"unknownId":{"$ref":"https://thecitizenaudit.org/schemas/platform-common.schema.json#/$defs/unknownId"},"description":{"$ref":"https://thecitizenaudit.org/schemas/platform-common.schema.json#/$defs/nonEmptyString"},"category":{"enum":["missing_record","incomplete_record","unresolvable_classification","estimate","scope_exclusion","conflicting_evidence","pending_verification"]},"reasonUnresolved":{"$ref":"https://thecitizenaudit.org/schemas/platform-common.schema.json#/$defs/nonEmptyString"},"effectOnConclusion":{"enum":["no_material_effect","may_affect_subsidiary_finding","may_affect_overall_conclusion","prevents_conclusion"]},"evidenceNeeded":{"type":"string"},"auditIds":{"$ref":"https://thecitizenaudit.org/schemas/platform-common.schema.json#/$defs/auditIdArray"},"findingIds":{"$ref":"https://thecitizenaudit.org/schemas/platform-common.schema.json#/$defs/findingIdArray"},"status":{"enum":["open","resolved","superseded"]}}}
